setup.py
get_helper/__init__.py
get_helper/get_response.py
get_helper.egg-info/PKG-INFO
get_helper.egg-info/SOURCES.txt
get_helper.egg-info/dependency_links.txt
get_helper.egg-info/requires.txt
get_helper.egg-info/top_level.txt