Metadata-Version: 1.0
Name: get-helper
Version: 0.2.0
Summary: Library module for getting a response using requests
Home-page: UNKNOWN
Author: AlexeiSimonov
Author-email: sushka2820655@yandex.ru
License: MIT
Platform: UNKNOWN
